passagemath_sympow/__init__.py
passagemath_sympow-10.6.43.dist-info/RECORD
passagemath_sympow-10.6.43.dist-info/WHEEL
passagemath_sympow-10.6.43.dist-info/top_level.txt
passagemath_sympow-10.6.43.dist-info/METADATA
sage_wheels/bin/sympow
sage_wheels/libexec/sympow/new_data
sage_wheels/share/sympow/standard1.gp
sage_wheels/share/sympow/standard2.gp
sage_wheels/share/sympow/standard3.gp
sage_wheels/share/sympow/datafiles/A018S.txt
sage_wheels/share/sympow/datafiles/param_data
sage_wheels/share/sympow/datafiles/M02HM.txt
sage_wheels/share/sympow/datafiles/A016M.txt
sage_wheels/share/sympow/datafiles/A014S.txt
sage_wheels/share/sympow/datafiles/A01OS.txt
sage_wheels/share/sympow/datafiles/A015S.txt
sage_wheels/share/sympow/datafiles/A017M.txt
sage_wheels/share/sympow/datafiles/A019S.txt
sage_wheels/share/sympow/datafiles/m02EM.txt
sage_wheels/share/sympow/datafiles/A012S.txt
sage_wheels/share/sympow/datafiles/M02LS.txt
sage_wheels/share/sympow/datafiles/m01EM.txt
sage_wheels/share/sympow/datafiles/A013S.txt
sage_wheels/share/sympow/datafiles/A012M.txt
sage_wheels/share/sympow/datafiles/M02LM.txt
sage_wheels/share/sympow/datafiles/m01ES.txt
sage_wheels/share/sympow/datafiles/A013M.txt
sage_wheels/share/sympow/datafiles/A018M.txt
sage_wheels/share/sympow/datafiles/M02HS.txt
sage_wheels/share/sympow/datafiles/A016S.txt
sage_wheels/share/sympow/datafiles/A014M.txt
sage_wheels/share/sympow/datafiles/A01OM.txt
sage_wheels/share/sympow/datafiles/A015M.txt
sage_wheels/share/sympow/datafiles/A017S.txt
sage_wheels/share/sympow/datafiles/A019M.txt
sage_wheels/share/sympow/datafiles/m02ES.txt
sage/all__sagemath_sympow.py
sage/lfunctions/all__sagemath_sympow.py
sage/lfunctions/sympow.py
sage/libs/sympow.abi3.so
sage/libs/sympow.pyx
sage/libs/all__sagemath_sympow.py
